{
  "/__docusaurus/debug-5ff": {
    "__comp": "__comp---theme-debug-config-23-a-2ff",
    "__context": {
      "plugin": "plugin---docusaurus-debugb-38-ad3"
    }
  },
  "/__docusaurus/debug/config-5ba": {
    "__comp": "__comp---theme-debug-config-23-a-2ff",
    "__context": {
      "plugin": "plugin---docusaurus-debugb-38-ad3"
    }
  },
  "/__docusaurus/debug/content-a2b": {
    "__comp": "__comp---theme-debug-contentba-8-ce7",
    "__context": {
      "plugin": "plugin---docusaurus-debugb-38-ad3"
    },
    "__props": "__props---docusaurus-debug-content-3-c-0-be2"
  },
  "/__docusaurus/debug/globalData-c3c": {
    "__comp": "__comp---theme-debug-global-dataede-0fa",
    "__context": {
      "plugin": "plugin---docusaurus-debugb-38-ad3"
    }
  },
  "/__docusaurus/debug/metadata-156": {
    "__comp": "__comp---theme-debug-site-metadata-68-e-3d4",
    "__context": {
      "plugin": "plugin---docusaurus-debugb-38-ad3"
    }
  },
  "/__docusaurus/debug/registry-88c": {
    "__comp": "__comp---theme-debug-registry-679-501",
    "__context": {
      "plugin": "plugin---docusaurus-debugb-38-ad3"
    }
  },
  "/__docusaurus/debug/routes-000": {
    "__comp": "__comp---theme-debug-routes-946-699",
    "__context": {
      "plugin": "plugin---docusaurus-debugb-38-ad3"
    }
  },
  "/blog-b2f": {
    "__comp": "__comp---theme-blog-list-pagea-6-a-7ba",
    "__context": {
      "plugin": "plugin---blog-369-22e"
    },
    "sidebar": "sidebar---blog-814-8ac",
    "items": [
      {
        "content": "content---blog-766-e3c"
      },
      {
        "content": "content---blogf-4-f-cd7"
      },
      {
        "content": "content---blog-871-381"
      },
      {
        "content": "content---blog-925-e00"
      }
    ],
    "__props": "__props---blogc-15-573"
  },
  "/blog/archive-182": {
    "__comp": "__comp---theme-blog-archive-page-9-e-4-1d8",
    "__context": {
      "plugin": "plugin---blog-369-22e"
    },
    "__props": "__props---blog-archivef-81-229"
  },
  "/blog/authors-0b7": {
    "__comp": "__comp---theme-blog-pages-blog-authors-list-page-621-70c",
    "__context": {
      "data": {
        "blogMetadata": "blogMetadata---blog-authorsace-e7d"
      },
      "plugin": "plugin---blog-369-22e"
    },
    "sidebar": "sidebar---blog-814-8ac",
    "__props": "__props---blog-authorsef-8-44f"
  },
  "/blog/authors/all-sebastien-lorber-articles-4a1": {
    "__comp": "__comp---theme-blog-pages-blog-authors-posts-page-33-f-bd5",
    "__context": {
      "data": {
        "blogMetadata": "blogMetadata---blog-authorsace-e7d"
      },
      "plugin": "plugin---blog-369-22e"
    },
    "items": [
      {
        "content": "content---blog-766-e3c"
      },
      {
        "content": "content---blogf-4-f-cd7"
      },
      {
        "content": "content---blog-925-e00"
      }
    ],
    "sidebar": "sidebar---blog-814-8ac",
    "__props": "__props---blog-authors-all-sebastien-lorber-articlesc-9-c-639"
  },
  "/blog/authors/yangshun-a68": {
    "__comp": "__comp---theme-blog-pages-blog-authors-posts-page-33-f-bd5",
    "__context": {
      "data": {
        "blogMetadata": "blogMetadata---blog-authorsace-e7d"
      },
      "plugin": "plugin---blog-369-22e"
    },
    "items": [
      {
        "content": "content---blog-766-e3c"
      },
      {
        "content": "content---blog-871-381"
      },
      {
        "content": "content---blog-925-e00"
      }
    ],
    "sidebar": "sidebar---blog-814-8ac",
    "__props": "__props---blog-authors-yangshun-1-de-d0c"
  },
  "/blog/first-blog-post-89a": {
    "__comp": "__comp---theme-blog-post-pageccc-cab",
    "__context": {
      "data": {
        "blogMetadata": "blogMetadata---blog-authorsace-e7d"
      },
      "plugin": "plugin---blog-369-22e"
    },
    "sidebar": "sidebar---blog-814-8ac",
    "content": "content---blog-first-blog-poste-27-4a1"
  },
  "/blog/long-blog-post-9ad": {
    "__comp": "__comp---theme-blog-post-pageccc-cab",
    "__context": {
      "data": {
        "blogMetadata": "blogMetadata---blog-authorsace-e7d"
      },
      "plugin": "plugin---blog-369-22e"
    },
    "sidebar": "sidebar---blog-814-8ac",
    "content": "content---blog-long-blog-post-736-bc7"
  },
  "/blog/mdx-blog-post-e9f": {
    "__comp": "__comp---theme-blog-post-pageccc-cab",
    "__context": {
      "data": {
        "blogMetadata": "blogMetadata---blog-authorsace-e7d"
      },
      "plugin": "plugin---blog-369-22e"
    },
    "sidebar": "sidebar---blog-814-8ac",
    "content": "content---blog-mdx-blog-post-593-37b"
  },
  "/blog/tags-287": {
    "__comp": "__comp---theme-blog-tags-list-page-01-a-d0b",
    "__context": {
      "plugin": "plugin---blog-369-22e"
    },
    "sidebar": "sidebar---blog-814-8ac",
    "__props": "__props---blog-tags-3-a-2-fa2"
  },
  "/blog/tags/docusaurus-704": {
    "__comp": "__comp---theme-blog-tags-posts-page-687-b6c",
    "__context": {
      "plugin": "plugin---blog-369-22e"
    },
    "sidebar": "sidebar---blog-814-8ac",
    "items": [
      {
        "content": "content---blog-766-e3c"
      },
      {
        "content": "content---blogf-4-f-cd7"
      },
      {
        "content": "content---blog-871-381"
      },
      {
        "content": "content---blog-925-e00"
      }
    ],
    "__props": "__props---blog-tags-docusaurus-321-832"
  },
  "/blog/tags/facebook-858": {
    "__comp": "__comp---theme-blog-tags-posts-page-687-b6c",
    "__context": {
      "plugin": "plugin---blog-369-22e"
    },
    "sidebar": "sidebar---blog-814-8ac",
    "items": [
      {
        "content": "content---blog-766-e3c"
      }
    ],
    "__props": "__props---blog-tags-facebooke-5-a-514"
  },
  "/blog/tags/hello-299": {
    "__comp": "__comp---theme-blog-tags-posts-page-687-b6c",
    "__context": {
      "plugin": "plugin---blog-369-22e"
    },
    "sidebar": "sidebar---blog-814-8ac",
    "items": [
      {
        "content": "content---blog-766-e3c"
      },
      {
        "content": "content---blog-871-381"
      }
    ],
    "__props": "__props---blog-tags-hellof-82-2fd"
  },
  "/blog/tags/hola-00d": {
    "__comp": "__comp---theme-blog-tags-posts-page-687-b6c",
    "__context": {
      "plugin": "plugin---blog-369-22e"
    },
    "sidebar": "sidebar---blog-814-8ac",
    "items": [
      {
        "content": "content---blog-925-e00"
      }
    ],
    "__props": "__props---blog-tags-hola-5-e-9-9a3"
  },
  "/blog/welcome-d2b": {
    "__comp": "__comp---theme-blog-post-pageccc-cab",
    "__context": {
      "data": {
        "blogMetadata": "blogMetadata---blog-authorsace-e7d"
      },
      "plugin": "plugin---blog-369-22e"
    },
    "sidebar": "sidebar---blog-814-8ac",
    "content": "content---blog-welcomed-9-f-ffb"
  },
  "/helloReact-77a": {
    "__comp": "__comp---site-src-pages-hello-react-js-06-f-dd2",
    "__context": {
      "plugin": "plugin---hello-reacta-74-9d0"
    },
    "config": "config---hello-react-5-e-9-f93"
  },
  "/docs-f6c": {
    "__comp": "__comp---theme-docs-root-5-e-9-0b6",
    "__context": {
      "plugin": "plugin---docsaba-d7c"
    }
  },
  "/docs-467": {
    "__comp": "__comp---theme-doc-version-roota-7-b-5de",
    "__props": "__props---docs-005-788"
  },
  "/docs-c65": {
    "__comp": "__comp---theme-doc-roota-94-67a"
  },
  "/docs/intro-61d": {
    "__comp": "__comp---theme-doc-item-178-a40",
    "content": "content---docs-intro-0-e-3-be1"
  },
  "/docs/L0/0/intro-af2": {
    "__comp": "__comp---theme-doc-item-178-a40",
    "content": "content---docs-l-0-0-introef-9-8b7"
  },
  "/docs/L0/1/-5c0": {
    "__comp": "__comp---theme-doc-item-178-a40",
    "content": "content---docs-l-0-1-a-7-d-d48"
  },
  "/docs/L0/1/1-1/1-1-90c": {
    "__comp": "__comp---theme-doc-item-178-a40",
    "content": "content---docs-l-0-1-1-1-1-1-efa-8d0"
  },
  "/docs/L0/1/1-2/1-2-10b": {
    "__comp": "__comp---theme-doc-item-178-a40",
    "content": "content---docs-l-0-1-1-2-1-286-b-4c9"
  },
  "/docs/L0/1/1-3/1-3-541": {
    "__comp": "__comp---theme-doc-item-178-a40",
    "content": "content---docs-l-0-1-1-3-1-3-fa-2-f82"
  },
  "/docs/L0/2/-158": {
    "__comp": "__comp---theme-doc-item-178-a40",
    "content": "content---docs-l-0-2-1-aa-608"
  },
  "/docs/L0/2/2-1/2-1-085": {
    "__comp": "__comp---theme-doc-item-178-a40",
    "content": "content---docs-l-0-2-2-1-2-1371-ad4"
  },
  "/docs/L0/2/2-2/2-2-066": {
    "__comp": "__comp---theme-doc-item-178-a40",
    "content": "content---docs-l-0-2-2-2-2-25-d-9-578"
  },
  "/docs/L0/2/2-3/2-3-cd5": {
    "__comp": "__comp---theme-doc-item-178-a40",
    "content": "content---docs-l-0-2-2-3-2-3-f-99-58f"
  },
  "/docs/L0/3/-bb5": {
    "__comp": "__comp---theme-doc-item-178-a40",
    "content": "content---docs-l-0-3-d-7-a-23f"
  },
  "/docs/L0/3/3-1/3-1-073": {
    "__comp": "__comp---theme-doc-item-178-a40",
    "content": "content---docs-l-0-3-3-1-3-1-a-41-598"
  },
  "/docs/L0/3/3-2/3-2-5df": {
    "__comp": "__comp---theme-doc-item-178-a40",
    "content": "content---docs-l-0-3-3-2-3-2-daf-611"
  },
  "/docs/L0/3/3-3/3-3-a31": {
    "__comp": "__comp---theme-doc-item-178-a40",
    "content": "content---docs-l-0-3-3-3-3-3-f-23-ae0"
  },
  "/docs/L0/accueil-9d6": {
    "__comp": "__comp---theme-doc-item-178-a40",
    "content": "content---docs-l-0-accueilca-0-860"
  },
  "/docs/L0/C/conclusion-e99": {
    "__comp": "__comp---theme-doc-item-178-a40",
    "content": "content---docs-l-0-c-conclusion-826-82f"
  },
  "/docs/L0/fiche-347": {
    "__comp": "__comp---theme-doc-item-178-a40",
    "content": "content---docs-l-0-fiche-0-ca-9ec"
  },
  "/docs/L0/howto-326": {
    "__comp": "__comp---theme-doc-item-178-a40",
    "content": "content---docs-l-0-howto-174-a70"
  },
  "/manuel-4e2": {
    "__comp": "__comp---theme-docs-root-5-e-9-0b6",
    "__context": {
      "plugin": "plugin---manuel-590-8a8"
    }
  },
  "/manuel-5e8": {
    "__comp": "__comp---theme-doc-version-roota-7-b-5de",
    "__props": "__props---manuele-49-cb9"
  },
  "/manuel-711": {
    "__comp": "__comp---theme-doc-roota-94-67a"
  },
  "/manuel/art-564": {
    "__comp": "__comp---theme-doc-item-178-a40",
    "content": "content---manuel-art-8-ad-5a8"
  },
  "/manuel/bonheur-683": {
    "__comp": "__comp---theme-doc-item-178-a40",
    "content": "content---manuel-bonheur-299-952"
  },
  "/manuel/conscience-998": {
    "__comp": "__comp---theme-doc-item-178-a40",
    "content": "content---manuel-consciencef-6-e-b09"
  },
  "/manuel/devoir-021": {
    "__comp": "__comp---theme-doc-item-178-a40",
    "content": "content---manuel-devoir-718-f22"
  },
  "/manuel/etat-5ef": {
    "__comp": "__comp---theme-doc-item-178-a40",
    "content": "content---manuel-etateaf-7cd"
  },
  "/manuel/inconscient-bb8": {
    "__comp": "__comp---theme-doc-item-178-a40",
    "content": "content---manuel-inconscient-4-fe-777"
  },
  "/manuel/intro-3a2": {
    "__comp": "__comp---theme-doc-item-178-a40",
    "content": "content---manuel-introffb-4b9"
  },
  "/methode-23e": {
    "__comp": "__comp---theme-docs-root-5-e-9-0b6",
    "__context": {
      "plugin": "plugin---methodeeea-444"
    }
  },
  "/methode-671": {
    "__comp": "__comp---theme-doc-version-roota-7-b-5de",
    "__props": "__props---methodee-2-b-bd4"
  },
  "/methode-ee1": {
    "__comp": "__comp---theme-doc-roota-94-67a"
  },
  "/methode/1/1-1/1-1-cee": {
    "__comp": "__comp---theme-doc-item-178-a40",
    "content": "content---methode-1-1-1-1-1689-c8c"
  },
  "/methode/1/1-2/1-2-29d": {
    "__comp": "__comp---theme-doc-item-178-a40",
    "content": "content---methode-1-1-2-1-241-d-c09"
  },
  "/methode/1/1-3/1-3-1fe": {
    "__comp": "__comp---theme-doc-item-178-a40",
    "content": "content---methode-1-1-3-1-386-d-dcf"
  },
  "/methode/2/2-1/2-1-622": {
    "__comp": "__comp---theme-doc-item-178-a40",
    "content": "content---methode-2-2-1-2-1947-589"
  },
  "/methode/2/2-2/2-2-0ae": {
    "__comp": "__comp---theme-doc-item-178-a40",
    "content": "content---methode-2-2-2-2-2-a-7-c-f21"
  },
  "/methode/2/2-3/2-3-553": {
    "__comp": "__comp---theme-doc-item-178-a40",
    "content": "content---methode-2-2-3-2-3-e-59-01a"
  },
  "/methode/3/-290": {
    "__comp": "__comp---theme-doc-item-178-a40",
    "content": "content---methode-3-28-a-0f9"
  },
  "/methode/intro-d04": {
    "__comp": "__comp---theme-doc-item-178-a40",
    "content": "content---methode-intro-3-dc-cf6"
  },
  "/methode/methode/1-4f1": {
    "__comp": "__comp---theme-doc-category-generated-index-page-14-e-640",
    "__props": "__props---methode-methode-1-ad-6-aa0"
  },
  "/methode/methode/2-83a": {
    "__comp": "__comp---theme-doc-category-generated-index-page-14-e-640",
    "__props": "__props---methode-methode-2699-395"
  },
  "/-fd5": {
    "__comp": "__comp---theme-mdx-page-1-f-3-b90",
    "__context": {
      "plugin": "plugin---hello-reacta-74-9d0"
    },
    "content": "content---e-7-c-0a5"
  }
}